ribosome/__init__.py
ribosome/constants.py
ribosome/scmtools/__init__.py
ribosome/scmtools/errors.py
ribosome/scmtools/git.py
ribosome/scmtools/hg.py
ribosome/scmtools/utils.py
ribosome.tool-0.6.6.dist-info/LICENSE
ribosome.tool-0.6.6.dist-info/METADATA
ribosome.tool-0.6.6.dist-info/WHEEL
ribosome.tool-0.6.6.dist-info/entry_points.txt
ribosome.tool-0.6.6.dist-info/top_level.txt
ribosome.tool-0.6.6.dist-info/RECORD
