Metadata-Version: 2.1
Name: ribosome.tool
Version: 0.6.6
Summary: Yet another project deploy and release tool
Home-page: https://github.com/alexandervpetrov/ribosome
Author: Sashko Petrov
Author-email: alexandervpetrov@gmail.com
License: MIT
Keywords: build deploy release
Platform: UNKNOWN
Classifier: Development Status :: 4 - Beta
Classifier: Environment :: Console
Classifier: Intended Audience :: Developers
Classifier: Natural Language :: English
Classifier: License :: OSI Approved :: MIT License
Classifier: Operating System :: POSIX :: Linux
Classifier: Programming Language :: Python
Classifier: Programming Language :: Python :: 3.6
Classifier: Topic :: Software Development :: Build Tools
Classifier: Topic :: System :: Installation/Setup
Classifier: Topic :: System :: Software Distribution
Requires-Python: >=3.6
Requires-Dist: click
Requires-Dist: ruamel.yaml
Requires-Dist: coloredlogs
Requires-Dist: boto3
Requires-Dist: fabric3
Requires-Dist: requests
